zanonymity/__init__.py
zanonymity/evaluate_category.py
zanonymity/evaluate_output.py
zanonymity/study_output.py
zanonymity/utils.py
zanonymity/zanon.py
zanon-0.3.2.dist-info/LICENSE
zanon-0.3.2.dist-info/METADATA
zanon-0.3.2.dist-info/WHEEL
zanon-0.3.2.dist-info/top_level.txt
zanon-0.3.2.dist-info/RECORD
