Metadata-Version: 2.1
Name: zanon
Version: 0.3.2
Summary: A module for z-anonymity
Home-page: https://gitlab.com/pimcity/wp2/zeta-anonymity
Author: SmartData@PoliTO
Author-email: s251325@studenti.polito.it
License: UNKNOWN
Platform: UNKNOWN
Classifier: Programming Language :: Python :: 3
Classifier: License :: OSI Approved :: GNU General Public License v3 (GPLv3)
Classifier: Operating System :: OS Independent
Requires-Python: >=3.6
